structly-1.0.1.dist-info/METADATA
structly-1.0.1.dist-info/WHEEL
structly-1.0.1.dist-info/licenses/LICENSE
structly/__init__.py
structly/_structly.pyd
structly/exceptions.py
structly/models/__init__.py
structly/models/config.py
structly/models/field_spec.py
structly/parser.py
structly-1.0.1.dist-info/RECORD
