Metadata-Version: 2.4
Name: structly
Version: 1.0.1
Classifier: Programming Language :: Python :: 3
Classifier: Programming Language :: Rust
Classifier: License :: OSI Approved :: MIT License
Classifier: Operating System :: OS Independent
Requires-Dist: pydantic>=2.6
Requires-Dist: pytest>=8.0 ; extra == 'dev'
Requires-Dist: pytest-cov>=5.0 ; extra == 'dev'
Requires-Dist: coverage-badge>=1.1 ; extra == 'dev'
Requires-Dist: maturin>=1.6 ; extra == 'dev'
Requires-Dist: black>=24.4.0 ; extra == 'dev'
Requires-Dist: isort>=5.13 ; extra == 'dev'
Requires-Dist: psutil>=5.9 ; extra == 'dev'
Provides-Extra: dev
License-File: LICENSE
Summary: High-performance text/logs parser (e.g., whois, nuclei, dns/dhcp logs) with Rust core
Author-email: Nikola Stankovic <nstankovic.bg@proton.me>
License: MIT
Requires-Python: >=3.9
